pyl4c/__init__.py
pyl4c/ease2.py
pyl4c/epsg.py
pyl4c/science.py
pyl4c/spatial.py
pyl4c/stats.py
pyl4c/towers.py
pyl4c/utils.py
pyl4c/apps/__init__.py
pyl4c/apps/nature.py
pyl4c/apps/resample.py
pyl4c/apps/calibration/__init__.py
pyl4c/apps/calibration/mcmc.py
pyl4c/apps/calibration/optimize.py
pyl4c/apps/l4c/__init__.py
pyl4c/apps/l4c/core.py
pyl4c/data/__init__.py
pyl4c/data/fixtures.py
pyl4c/data/files/SMAP_BPLUT_2020-07-31.csv
pyl4c/data/files/ancillary_file_paths.yaml
pyl4c/data/files/config_L4C_MCMC_calibration.yaml
pyl4c/data/files/config_L4C_MCMC_calibration_V8.yaml
pyl4c/data/files/config_L4C_calibration.yaml
pyl4c/data/files/config_L4C_calibration_V8.yaml
pyl4c/lib/__init__.py
pyl4c/lib/cli.py
pyl4c/lib/modis.py
pyl4c/lib/netcdf.py
pyl4c/lib/tcf.py
pyl4c/lib/transcom.py
pyl4c/lib/transpiration.py
pyl4c/tests/__init__.py
pyl4c/tests/calibration.py
pyl4c/tests/l4c.py
pyl4c/tests/tests.py
pyl4c/tests/transpiration.py
pyl4c-0.18.1.dist-info/LICENSE
pyl4c-0.18.1.dist-info/METADATA
pyl4c-0.18.1.dist-info/WHEEL
pyl4c-0.18.1.dist-info/top_level.txt
pyl4c-0.18.1.dist-info/RECORD
