Metadata-Version: 2.1
Name: pyl4c
Version: 0.18.1
Summary: Python tools for working with SMAP L4C data
Author: K. Arthur Endsley
Author-email: arthur.endsley@ntsg.umt.edu
Classifier: Programming Language :: Python :: 3
Classifier: Development Status :: 3 - Alpha
Classifier: Intended Audience :: Science/Research
Classifier: Topic :: Scientific/Engineering
Classifier: Topic :: Scientific/Engineering :: GIS
Requires-Python: >=3.5
License-File: LICENSE
Requires-Dist: numpy>=1.13.3
Requires-Dist: scipy>=1.3
Requires-Dist: h5py>=2.10.0
Requires-Dist: GDAL>=2.2.0
Requires-Dist: affine>=2.3.0
Requires-Dist: cached-property>=1.5.1
Requires-Dist: pyproj>=2.5.0
Requires-Dist: PyYAML>=6.0.0
Provides-Extra: calibration
Requires-Dist: pandas>=2.0.0; extra == "calibration"
Requires-Dist: nlopt>=2.6.0; extra == "calibration"
Requires-Dist: netCDF4>=1.5.0; extra == "calibration"
Requires-Dist: fire>=0.4.0; extra == "calibration"
Requires-Dist: matplotlib>=2.1.1; extra == "calibration"
Requires-Dist: pymc>=5.0.0; extra == "calibration"
Requires-Dist: arviz>=0.12.0; extra == "calibration"
Requires-Dist: PyYAML>=6.0.0; extra == "calibration"
Provides-Extra: cli
Requires-Dist: fire>=0.4.0; extra == "cli"
Requires-Dist: rasterstats>=0.13.1; extra == "cli"
Provides-Extra: docs
Requires-Dist: pdoc3>=0.9.2; extra == "docs"
Provides-Extra: netcdf
Requires-Dist: netCDF4>=1.5.0; extra == "netcdf"
Provides-Extra: transcom
Requires-Dist: scikit-image>=0.21.0; extra == "transcom"
